32_32_schoolbook_v3.v
module base_multiplier #(parameter base_mult = 32)(
    input clk,
    input [base_mult-1:0] x,
    input [base_mult-1:0] y,
    output reg [2*base_mult-1:0] out
);
    always @(posedge clk) begin
        out <= x * y;
    end
endmodule


module BRAM_2_2_grp_multiplier #(parameter base_mult = 32, parameter size = 128)(
    input clk,
    input [base_mult-1:0] x1,
    input [base_mult-1:0] y1,
    output reg [base_mult-1:0] out,
    output reg valid_out
);
    localparam num_blocks = size / (base_mult * 2);  // number of 2-word blocks
    localparam num_steps = num_blocks * num_blocks;

    reg [base_mult-1:0] a [0:2*num_blocks-1];
    reg [base_mult-1:0] b [0:2*num_blocks-1];

    integer count = 0;
    integer a_idx = 1;
    integer b_idx = 1;

    // Input packing registers
    reg [base_mult*2-1:0] in1, in2;

    // Output from base multiplier
    wire [4*base_mult-1:0] mult_result;

    // Pipeline registers to delay shift and accumulation
    reg [31:0] shift_pipe1, shift_pipe2, shift_pipe3;
    reg [4*base_mult-1:0] mult_pipe;

    // Accumulator
    reg [2*size-1:0] final_out = 0;
    reg [2*size-1:0] final_out_latched = 0;
    reg accumulation_done = 0;

    // Instantiate multiplier
    base_multiplier #(base_mult * 2) dut (
        .clk(clk),
        .x(in1),
        .y(in2),
        .out(mult_result)
    );

    // Stage 1: Collect all 2*num_blocks elements
    always @(posedge clk) begin
        if (count < 2*num_blocks) begin
            a[count] <= x1;
            b[count] <= y1;
        end
        count <= count + 1;
    end

    // Stage 2: Feed packed inputs for multiplication
    always @(posedge clk) begin
        if(a_idx <= num_blocks && b_idx <= num_blocks) begin
            if(count % 2 == 0 && count != 0) begin
                in1 <= {a[2*(a_idx-1)+1], a[2*(a_idx-1)]};
                in2 <= {b[2*(b_idx-1)+1], b[2*(b_idx-1)]};

                shift_pipe1 <= base_mult * 2 * (a_idx + b_idx - 2);
                
                // Update indices
                if (a_idx == num_blocks) begin
                    a_idx <= 1;
                    b_idx <= b_idx + 1;
                end
                else if (a_idx < num_blocks) begin
                    a_idx <= a_idx + 1;
                    b_idx <= b_idx;
                end
            end
        end
    end

    // Stage 3: Pipeline multiplier output and shift amount
    always @(posedge clk) begin
        shift_pipe2 <= shift_pipe1;
        mult_pipe <= mult_result;
    end

    always @(posedge clk) begin
        shift_pipe3 <= shift_pipe2;
    end

    // Stage 4: Accumulate shifted product
    integer step_counter = 0;
    always @(posedge clk) begin
        if ((count % 2 == 1) && (count >= 5) && (step_counter < num_steps)) begin
            final_out <= final_out + (mult_pipe << shift_pipe3);
            step_counter <= step_counter + 1;
            $display("step counter =  %d, num_steps = %d", step_counter, num_steps);
        end else if (step_counter == num_steps) begin
            final_out_latched <= final_out;
            accumulation_done <= 1;
        end
    end

    // Stage 5: Output 32-bit chunks sequentially
    reg [31:0] out_idx = 0;
    always @(posedge clk) begin
        if (accumulation_done && out_idx < 2*size) begin
            out <= final_out_latched[out_idx +: 32];
            out_idx <= out_idx + 32;
            valid_out <= 1;
        end else begin
            valid_out <= 0;
        end
    end
endmodule

module BRAM_4_2_grp_multiplier #(parameter base_mult = 32, parameter size = 128)(
    input clk,
    input [base_mult-1:0] x1,
    input [base_mult-1:0] x2,
    input [base_mult-1:0] y1,
    input [base_mult-1:0] y2,
    output reg [base_mult-1:0] out,
    output reg valid_out
);
    localparam num_blocks = size / (base_mult * 2);  // number of 2-word blocks
    localparam num_steps = num_blocks * num_blocks;

    reg [base_mult-1:0] a [0:2*num_blocks-1];
    reg [base_mult-1:0] b [0:2*num_blocks-1];

    integer count = 0;
    integer a_idx = 1;
    integer b_idx = 1;

    // Input packing registers
    reg [base_mult*2-1:0] in1, in2;

    // Output from base multiplier
    wire [4*base_mult-1:0] mult_result;

    // Pipeline registers to delay shift and accumulation
    reg [31:0] shift_pipe1, shift_pipe2, shift_pipe3;
    reg [4*base_mult-1:0] mult_pipe;

    // Accumulator
    reg [2*size-1:0] final_out = 0;
    reg [2*size-1:0] final_out_latched = 0;
    reg accumulation_done = 0;

    // Instantiate multiplier
    base_multiplier #(base_mult * 2) dut (
        .clk(clk),
        .x(in1),
        .y(in2),
        .out(mult_result)
    );

    // Stage 1: Collect all 2*num_blocks elements
    always @(posedge clk) begin
        if (count < 2*num_blocks) begin
            a[count] <= x1;
            a[count+1] <= x2;
            b[count] <= y1;
            b[count+1] <= y2;
        end
        count <= count + 2;
    end

    // Stage 2: Feed packed inputs for multiplication
    always @(posedge clk) begin
        if(a_idx <= num_blocks && b_idx <= num_blocks) begin
            if(count % 2 == 0 && count != 0) begin
                in1 <= {a[2*(a_idx-1)+1], a[2*(a_idx-1)]};
                in2 <= {b[2*(b_idx-1)+1], b[2*(b_idx-1)]};

                shift_pipe1 <= base_mult * 2 * (a_idx + b_idx - 2);
                
                // Update indices
                if (a_idx == num_blocks) begin
                    a_idx <= 1;
                    b_idx <= b_idx + 1;
                end
                else if (a_idx < num_blocks) begin
                    a_idx <= a_idx + 1;
                    b_idx <= b_idx;
                end
            end
        end
    end

    // Stage 3: Pipeline multiplier output and shift amount
    always @(posedge clk) begin
        shift_pipe2 <= shift_pipe1;
        mult_pipe <= mult_result;
    end

    always @(posedge clk) begin
        shift_pipe3 <= shift_pipe2;
    end

    // Stage 4: Accumulate shifted product
    integer step_counter = 0;
    always @(posedge clk) begin
        if ((count % 2 == 0) && (count >= 8) && (step_counter < num_steps)) begin
            final_out <= final_out + (mult_pipe << shift_pipe3);
            step_counter <= step_counter + 1;
            $display("step counter =  %d, num_steps = %d", step_counter, num_steps);
        end else if (step_counter == num_steps) begin
            final_out_latched <= final_out;
            accumulation_done <= 1;
        end
    end

    // Stage 5: Output 32-bit chunks sequentially
    reg [31:0] out_idx = 0;
    always @(posedge clk) begin
        if (accumulation_done && out_idx < 2*size) begin
            out <= final_out_latched[out_idx +: 32];
            out_idx <= out_idx + 32;
            valid_out <= 1;
        end else begin
            valid_out <= 0;
        end
    end
endmodule

module BRAM_2_1_grp_multiplier #(parameter base_mult = 32, parameter size = 128)(
    input clk,
    input [base_mult-1:0] x1,
    input [base_mult-1:0] y1,
    output reg [base_mult-1:0] out,
    output reg valid_out
);
    localparam num_blocks = size / (base_mult);  // number of 2-word blocks
    localparam num_steps = num_blocks * num_blocks;

    reg [base_mult-1:0] a [0:num_blocks-1];
    reg [base_mult-1:0] b [0:num_blocks-1];

    integer count = 0;
    integer a_idx = 1;
    integer b_idx = 1;

    // Input packing registers
    reg [base_mult-1:0] in1, in2;

    // Output from base multiplier
    wire [2*base_mult-1:0] mult_result;

    // Pipeline registers to delay shift and accumulation
    reg [31:0] shift_pipe1, shift_pipe2, shift_pipe3;
    reg [2*base_mult-1:0] mult_pipe;

    // Accumulator
    reg [2*size-1:0] final_out = 0;
    reg [2*size-1:0] final_out_latched = 0;
    reg accumulation_done = 0;

    // Instantiate multiplier
    base_multiplier #(base_mult) dut (
        .clk(clk),
        .x(in1),
        .y(in2),
        .out(mult_result)
    );

    // Stage 1: Collect all 2*num_blocks elements
    always @(posedge clk) begin
        if (count < num_blocks) begin
            a[count] <= x1;
            b[count] <= y1;
        end
        count <= count + 1;
    end

    // Stage 2: Feed packed inputs for multiplication
    always @(posedge clk) begin
        if(a_idx <= num_blocks && b_idx <= num_blocks) begin
            if(count > 0) begin
                in1 <= a[(a_idx-1)];
                in2 <= b[(b_idx-1)];

                shift_pipe1 <= base_mult * (a_idx + b_idx - 2);
                
                // Update indices
                if (a_idx == num_blocks) begin
                    a_idx <= 1;
                    b_idx <= b_idx + 1;
                end
                else if (a_idx < num_blocks) begin
                    a_idx <= a_idx + 1;
                    b_idx <= b_idx;
                end
            end
        end
    end

    // Stage 3: Pipeline multiplier output and shift amount
    always @(posedge clk) begin
        shift_pipe2 <= shift_pipe1;
        mult_pipe <= mult_result;
    end

    always @(posedge clk) begin
        shift_pipe3 <= shift_pipe2;
    end

    // Stage 4: Accumulate shifted product
    integer step_counter = 0;
    always @(posedge clk) begin
        if ((count >= 4) && (step_counter < num_steps)) begin
            final_out <= final_out + (mult_pipe << shift_pipe3);
            step_counter <= step_counter + 1;
            $display("step counter =  %d, num_steps = %d", step_counter, num_steps);
        end else if (step_counter == num_steps) begin
            final_out_latched <= final_out;
            accumulation_done <= 1;
        end
    end

    // Stage 5: Output 32-bit chunks sequentially
    reg [31:0] out_idx = 0;
    always @(posedge clk) begin
        if (accumulation_done && out_idx < 2*size) begin
            out <= final_out_latched[out_idx +: 32];
            out_idx <= out_idx + 32;
            valid_out <= 1;
        end else begin
            valid_out <= 0;
        end
    end
endmodule

module BRAM_4_1_grp_multiplier #(parameter base_mult = 32, parameter size = 128)(
    input clk,
    input [base_mult-1:0] x1,
    input [base_mult-1:0] x2,
    input [base_mult-1:0] y1,
    input [base_mult-1:0] y2,
    output reg [base_mult-1:0] out,
    output reg valid_out
);
    localparam num_blocks = size / (base_mult);  // number of 2-word blocks
    localparam num_steps = num_blocks * num_blocks;

    reg [base_mult-1:0] a [0:num_blocks-1];
    reg [base_mult-1:0] b [0:num_blocks-1];

    integer count = 0;
    integer a_idx = 1;
    integer b_idx = 1;

    // Input packing registers
    reg [base_mult-1:0] in1, in2;

    // Output from base multiplier
    wire [2*base_mult-1:0] mult_result;

    // Pipeline registers to delay shift and accumulation
    reg [31:0] shift_pipe1, shift_pipe2, shift_pipe3;
    reg [2*base_mult-1:0] mult_pipe;

    // Accumulator
    reg [2*size-1:0] final_out = 0;
    reg [2*size-1:0] final_out_latched = 0;
    reg accumulation_done = 0;

    // Instantiate multiplier
    base_multiplier #(base_mult) dut (
        .clk(clk),
        .x(in1),
        .y(in2),
        .out(mult_result)
    );

    // Stage 1: Collect all 2*num_blocks elements
    always @(posedge clk) begin
        if (count < num_blocks) begin
            a[count] <= x1;
            a[count + 1] <= x2;
            b[count] <= y1;
            b[count + 1] <= y2;
        end
        count <= count + 2;
    end

    // Stage 2: Feed packed inputs for multiplication
    always @(posedge clk) begin
        if(a_idx <= num_blocks && b_idx <= num_blocks) begin
            if(count > 0) begin
                in1 <= a[(a_idx-1)];
                in2 <= b[(b_idx-1)];

                shift_pipe1 <= base_mult * (a_idx + b_idx - 2);
                
                // Update indices
                if (a_idx == num_blocks) begin
                    a_idx <= 1;
                    b_idx <= b_idx + 1;
                end
                else if (a_idx < num_blocks) begin
                    a_idx <= a_idx + 1;
                    b_idx <= b_idx;
                end
            end
        end
    end

    // Stage 3: Pipeline multiplier output and shift amount
    always @(posedge clk) begin
        shift_pipe2 <= shift_pipe1;
        mult_pipe <= mult_result;
    end

    always @(posedge clk) begin
        shift_pipe3 <= shift_pipe2;
    end

    // Stage 4: Accumulate shifted product
    integer step_counter = 0;
    always @(posedge clk) begin
        if ((count >= 8) && (step_counter < num_steps)) begin
            final_out <= final_out + (mult_pipe << shift_pipe3);
            step_counter <= step_counter + 1;
            $display("step counter =  %d, num_steps = %d", step_counter, num_steps);
        end else if (step_counter == num_steps) begin
            final_out_latched <= final_out;
            accumulation_done <= 1;
        end
    end

    // Stage 5: Output 32-bit chunks sequentially
    reg [31:0] out_idx = 0;
    always @(posedge clk) begin
        if (accumulation_done && out_idx < 2*size) begin
            out <= final_out_latched[out_idx +: 32];
            out_idx <= out_idx + 32;
            valid_out <= 1;
        end else begin
            valid_out <= 0;
        end
    end
endmodule

parameterised_multipliers/32_32_schoolbook_tb.v
module test_bench;
    parameter base_mult = 64;
    parameter size = 2048; // for 2 blocks

    reg clk;
    reg [base_mult-1:0] x1;
    reg [base_mult-1:0] y1;
    
    reg [base_mult-1:0] x2;
    reg [base_mult-1:0] y2;
    wire [base_mult-1:0] out;
    wire valid_out;

    // Instantiate the module
    BRAM_4_1_grp_multiplier #(base_mult, size) dut (
        .clk(clk),
        .x1(x1),
        .x2(x2),
        .y1(y1),
        .y2(y2),
        .out(out),
        .valid_out(valid_out)
    );

    // Clock generation
    initial begin
        clk = 0;
        forever #5 clk = ~clk;
    end

    // Stimulus
    initial begin
        // Initialize inputs
        x1 = 32'd9;
        y1 = 32'd12;

        x2 = 32'd00;
        y2 = 32'd00;

        #10;
        x1 = 32'd00;
        y1 = 32'd00;

        x2 = 32'd00;
        y2 = 32'd00;        
        
        #10;
        x1 = 32'd00;
        y1 = 32'd00;

        x2 = 32'd00;
        y2 = 32'd00;
        #10;
        x1 = 32'd00;
        y1 = 32'd00;

        #10;
        x1 = 32'd00;
        y1 = 32'd00;

        x2 = 32'd00;
        y2 = 32'd00;
        #10;
        x1 = 32'd00;
        y1 = 32'd00;

        #10;
        x1 = 32'd00;
        y1 = 32'd00;
        x2 = 32'd00;
        y2 = 32'd00;
        // #10;
        // x1 = 32'd00;
        // y1 = 32'd00;

        #10;
        x1 = 32'd00;
        y1 = 32'd00;

        x2 = 32'd00;
        y2 = 32'd00;
        // #10;
        // x1 = 32'd00;
        // y1 = 32'd00;

        #10;
        x1 = 32'd00;
        y1 = 32'd00;
        x2 = 32'd00;
        y2 = 32'd00;
        // #10;
        // x1 = 32'd00;
        // y1 = 32'd00;

        #10;
        x1 = 32'd00;
        y1 = 32'd00;
        x2 = 32'd00;
        y2 = 32'd00;
        // x2 = 32'hCCCC_CCCC; // should not be stored (num_blocks=2)
        // y2 = 32'h3333_3333;

        #90000;

        $display("out =  %d", out);
        $finish;
    end

    initial begin
        $dumpfile("check.vcd");
        // $dumpvars(0, dut, dut.a[0], dut.a[1], dut.b[0], dut.b[1], dut.partial_out[0], dut.shift_amount[0], dut.partial_out[1], dut.shift_amount[1], dut.partial_out[2], dut.shift_amount[2],  dut.partial_out[3], dut.shift_amount[3],dut.in1, dut.in2, dut.outf);
        $dumpvars(0, dut, dut.a[0], dut.a[1], dut.b[0], dut.b[1], dut.shift_pipe1, dut.shift_pipe2, dut.mult_pipe, dut.in1, dut.in2, dut.final_out);
    end

    initial begin
        $monitor("total_out =  %h", out);
    end
endmodule

check.vcd
$date
	Tue Jun 03 11:38:45 2025
$end
$version
	Icarus Verilog
$end
$timescale
	1s
$end
$scope module test_bench $end
$scope module dut $end
$var wire 1 ! clk $end
$var wire 64 " x1 [63:0] $end
$var wire 64 # x2 [63:0] $end
$var wire 64 $ y1 [63:0] $end
$var wire 64 % y2 [63:0] $end
$var wire 128 & mult_result [127:0] $end
$var parameter 32 ' base_mult $end
$var parameter 32 ( num_blocks $end
$var parameter 64 ) num_steps $end
$var parameter 32 * size $end
$var reg 1 + accumulation_done $end
$var reg 4096 , final_out [4095:0] $end
$var reg 4096 - final_out_latched [4095:0] $end
$var reg 64 . in1 [63:0] $end
$var reg 64 / in2 [63:0] $end
$var reg 128 0 mult_pipe [127:0] $end
$var reg 64 1 out [63:0] $end
$var reg 32 2 out_idx [31:0] $end
$var reg 32 3 shift_pipe1 [31:0] $end
$var reg 32 4 shift_pipe2 [31:0] $end
$var reg 32 5 shift_pipe3 [31:0] $end
$var reg 1 6 valid_out $end
$var integer 32 7 a_idx [31:0] $end
$var integer 32 8 b_idx [31:0] $end
$var integer 32 9 count [31:0] $end
$var integer 32 : step_counter [31:0] $end
$scope module dut $end
$var wire 1 ! clk $end
$var wire 64 ; x [63:0] $end
$var wire 64 < y [63:0] $end
$var parameter 32 = base_mult $end
$var reg 128 > out [127:0] $end
$upscope $end
$upscope $end
$upscope $end
$scope module test_bench $end
$scope module dut $end
$var reg 64 ? \a[0] [63:0] $end
$upscope $end
$upscope $end
$scope module test_bench $end
$scope module dut $end
$var reg 64 @ \a[1] [63:0] $end
$upscope $end
$upscope $end
$scope module test_bench $end
$scope module dut $end
$var reg 64 A \b[0] [63:0] $end
$upscope $end
$upscope $end
$scope module test_bench $end
$scope module dut $end
$var reg 64 B \b[1] [63:0] $end
$upscope $end
$upscope $end
$enddefinitions $end
$comment Show the parameter values. $end
$dumpall
b1000000 =
b100000000000 *
b10000000000 )
b100000 (
b1000000 '
$end
#0
$dumpvars
bx B
bx A
bx @
bx ?
bx >
bx <
bx ;
b0 :
b0 9
b1 8
b1 7
x6
bx 5
bx 4
bx 3
b0 2
bx 1
bx 0
bx /
bx .
b0 -
b0 ,
0+
bx &
b0 %
b1100 $
b0 #
b1001 "
0!
$end
#5
b10 9
b0 B
b1100 A
b0 @
b1001 ?
06
1!
#10
0!
b0 $
b0 "
#15
b10 7
b0 3
b1100 /
b1100 <
b1001 .
b1001 ;
b100 9
1!
#20
0!
#25
b1101100 &
b1101100 >
b110 9
b11 7
b1000000 3
b0 .
b0 ;
b0 4
1!
#30
0!
#35
b0 5
b1101100 0
b1000000 4
b100 7
b10000000 3
b1000 9
b0 &
b0 >
1!
#40
0!
#45
b1010 9
b101 7
b11000000 3
b0 0
b10000000 4
b1000000 5
b1 :
b1101100 ,
1!
#50
0!
#55
b10 :
b10000000 5
b11000000 4
b110 7
b100000000 3
b1100 9
1!
#60
0!
#65
b1110 9
b111 7
b101000000 3
b100000000 4
b11000000 5
b11 :
1!
#70
0!
#75
b100 :
b100000000 5
b101000000 4
b1000 7
b110000000 3
b10000 9
1!
#80
0!
#85
b10010 9
b1001 7
b111000000 3
b110000000 4
b101000000 5
b101 :
1!
#90
0!
#95
b110 :
b110000000 5
b111000000 4
b1010 7
b1000000000 3
b10100 9
1!
#100
0!
#105
b10110 9
b1011 7
b1001000000 3
b1000000000 4
b111000000 5
b111 :
1!
#110
0!
#115
b1000 :
b1000000000 5
b1001000000 4
b1100 7
b1010000000 3
b11000 9
1!
#120
0!
#125
b11010 9
b1101 7
b1011000000 3
b1010000000 4
b1001000000 5
b1001 :
1!
#130
0!
#135
b1010 :
b1010000000 5
b1011000000 4
b1110 7
b1100000000 3
b11100 9
1!
#140
0!
#145
b11110 9
b1111 7
b1101000000 3
b1100000000 4
b1011000000 5
b1011 :
1!
#150
0!
#155
b1100 :
b1100000000 5
b1101000000 4
b10000 7
b1110000000 3
b100000 9
1!
#160
0!
#165
b100010 9
b10001 7
b1111000000 3
b1110000000 4
b1101000000 5
b1101 :
1!
#170
0!
#175
b1110 :
b1110000000 5
b1111000000 4
b10010 7
b10000000000 3
b100100 9
1!
#180
0!
#185
b100110 9
b10011 7
b10001000000 3
b10000000000 4
b1111000000 5
b1111 :
1!
#190
0!
#195
b10000 :
b10000000000 5
b10001000000 4
b10100 7
b10010000000 3
b101000 9
1!
#200
0!
#205
b101010 9
b10101 7
b10011000000 3
b10010000000 4
b10001000000 5
b10001 :
1!
#210
0!
#215
b10010 :
b10010000000 5
b10011000000 4
b10110 7
b10100000000 3
b101100 9
1!
#220
0!
#225
b101110 9
b10111 7
b10101000000 3
b10100000000 4
b10011000000 5
b10011 :
1!
#230
0!
#235
b10100 :
b10100000000 5
b10101000000 4
b11000 7
b10110000000 3
b110000 9
1!
#240
0!
#245
b110010 9
b11001 7
b10111000000 3
b10110000000 4
b10101000000 5
b10101 :
1!
#250
0!
#255
b10110 :
b10110000000 5
b10111000000 4
b11010 7
b11000000000 3
b110100 9
1!
#260
0!
#265
b110110 9
b11011 7
b11001000000 3
b11000000000 4
b10111000000 5
b10111 :
1!
#270
0!
#275
b11000 :
b11000000000 5
b11001000000 4
b11100 7
b11010000000 3
b111000 9
1!
#280
0!
#285
b111010 9
b11101 7
b11011000000 3
b11010000000 4
b11001000000 5
b11001 :
1!
#290
0!
#295
b11010 :
b11010000000 5
b11011000000 4
b11110 7
b11100000000 3
b111100 9
1!
#300
0!
#305
b111110 9
b11111 7
b11101000000 3
b11100000000 4
b11011000000 5
b11011 :
1!
#310
0!
#315
b11100 :
b11100000000 5
b11101000000 4
b100000 7
b11110000000 3
b1000000 9
1!
#320
0!
#325
b1000010 9
b10 8
b1 7
b11111000000 3
b11110000000 4
b11101000000 5
b11101 :
1!
#330
0!
#335
b11110 :
b11110000000 5
b11111000000 4
b10 7
b1000000 3
b0 /
b0 <
b1001 .
b1001 ;
b1000100 9
1!
#340
0!
#345
b1000110 9
b11 7
b10000000 3
b0 .
b0 ;
b1000000 4
b11111000000 5
b11111 :
1!
#350
0!
#355
b100000 :
b1000000 5
b10000000 4
b100 7
b11000000 3
b1001000 9
1!
#360
0!
#365
b1001010 9
b101 7
b100000000 3
b11000000 4
b10000000 5
b100001 :
1!
#370
0!
#375
b100010 :
b11000000 5
b100000000 4
b110 7
b101000000 3
b1001100 9
1!
#380
0!
#385
b1001110 9
b111 7
b110000000 3
b101000000 4
b100000000 5
b100011 :
1!
#390
0!
#395
b100100 :
b101000000 5
b110000000 4
b1000 7
b111000000 3
b1010000 9
1!
#400
0!
#405
b1010010 9
b1001 7
b1000000000 3
b111000000 4
b110000000 5
b100101 :
1!
#410
0!
#415
b100110 :
b111000000 5
b1000000000 4
b1010 7
b1001000000 3
b1010100 9
1!
#420
0!
#425
b1010110 9
b1011 7
b1010000000 3
b1001000000 4
b1000000000 5
b100111 :
1!
#430
0!
#435
b101000 :
b1001000000 5
b1010000000 4
b1100 7
b1011000000 3
b1011000 9
1!
#440
0!
#445
b1011010 9
b1101 7
b1100000000 3
b1011000000 4
b1010000000 5
b101001 :
1!
#450
0!
#455
b101010 :
b1011000000 5
b1100000000 4
b1110 7
b1101000000 3
b1011100 9
1!
#460
0!
#465
b1011110 9
b1111 7
b1110000000 3
b1101000000 4
b1100000000 5
b101011 :
1!
#470
0!
#475
b101100 :
b1101000000 5
b1110000000 4
b10000 7
b1111000000 3
b1100000 9
1!
#480
0!
#485
b1100010 9
b10001 7
b10000000000 3
b1111000000 4
b1110000000 5
b101101 :
1!
#490
0!
#495
b101110 :
b1111000000 5
b10000000000 4
b10010 7
b10001000000 3
b1100100 9
1!
#500
0!
#505
b1100110 9
b10011 7
b10010000000 3
b10001000000 4
b10000000000 5
b101111 :
1!
#510
0!
#515
b110000 :
b10001000000 5
b10010000000 4
b10100 7
b10011000000 3
b1101000 9
1!
#520
0!
#525
b1101010 9
b10101 7
b10100000000 3
b10011000000 4
b10010000000 5
b110001 :
1!
#530
0!
#535
b110010 :
b10011000000 5
b10100000000 4
b10110 7
b10101000000 3
b1101100 9
1!
#540
0!
#545
b1101110 9
b10111 7
b10110000000 3
b10101000000 4
b10100000000 5
b110011 :
1!
#550
0!
#555
b110100 :
b10101000000 5
b10110000000 4
b11000 7
b10111000000 3
b1110000 9
1!
#560
0!
#565
b1110010 9
b11001 7
b11000000000 3
b10111000000 4
b10110000000 5
b110101 :
1!
#570
0!
#575
b110110 :
b10111000000 5
b11000000000 4
b11010 7
b11001000000 3
b1110100 9
1!
#580
0!
#585
b1110110 9
b11011 7
b11010000000 3
b11001000000 4
b11000000000 5
b110111 :
1!
#590
0!
#595
b111000 :
b11001000000 5
b11010000000 4
b11100 7
b11011000000 3
b1111000 9
1!
#600
0!
#605
b1111010 9
b11101 7
b11100000000 3
b11011000000 4
b11010000000 5
b111001 :
1!
#610
0!
#615
b111010 :
b11011000000 5
b11100000000 4
b11110 7
b11101000000 3
b1111100 9
1!
#620
0!
#625
b1111110 9
b11111 7
b11110000000 3
b11101000000 4
b11100000000 5
b111011 :
1!
#630
0!
#635
b111100 :
b11101000000 5
b11110000000 4
b100000 7
b11111000000 3
b10000000 9
1!
#640
0!
#645
b10000010 9
b11 8
b1 7
b100000000000 3
b11111000000 4
b11110000000 5
b111101 :
1!
#650
0!
#655
b111110 :
b11111000000 5
b100000000000 4
b10 7
b10000000 3
b1001 .
b1001 ;
b10000100 9
1!
#660
0!
#665
b10000110 9
b11 7
b11000000 3
b0 .
b0 ;
b10000000 4
b100000000000 5
b111111 :
1!
#670
0!
#675
b1000000 :
b10000000 5
b11000000 4
b100 7
b100000000 3
b10001000 9
1!
#680
0!
#685
b10001010 9
b101 7
b101000000 3
b100000000 4
b11000000 5
b1000001 :
1!
#690
0!
#695
b1000010 :
b100000000 5
b101000000 4
b110 7
b110000000 3
b10001100 9
1!
#700
0!
#705
b10001110 9
b111 7
b111000000 3
b110000000 4
b101000000 5
b1000011 :
1!
#710
0!
#715
b1000100 :
b110000000 5
b111000000 4
b1000 7
b1000000000 3
b10010000 9
1!
#720
0!
#725
b10010010 9
b1001 7
b1001000000 3
b1000000000 4
b111000000 5
b1000101 :
1!
#730
0!
#735
b1000110 :
b1000000000 5
b1001000000 4
b1010 7
b1010000000 3
b10010100 9
1!
#740
0!
#745
b10010110 9
b1011 7
b1011000000 3
b1010000000 4
b1001000000 5
b1000111 :
1!
#750
0!
#755
b1001000 :
b1010000000 5
b1011000000 4
b1100 7
b1100000000 3
b10011000 9
1!
#760
0!
#765
b10011010 9
b1101 7
b1101000000 3
b1100000000 4
b1011000000 5
b1001001 :
1!
#770
0!
#775
b1001010 :
b1100000000 5
b1101000000 4
b1110 7
b1110000000 3
b10011100 9
1!
#780
0!
#785
b10011110 9
b1111 7
b1111000000 3
b1110000000 4
b1101000000 5
b1001011 :
1!
#790
0!
#795
b1001100 :
b1110000000 5
b1111000000 4
b10000 7
b10000000000 3
b10100000 9
1!
#800
0!
#805
b10100010 9
b10001 7
b10001000000 3
b10000000000 4
b1111000000 5
b1001101 :
1!
#810
0!
#815
b1001110 :
b10000000000 5
b10001000000 4
b10010 7
b10010000000 3
b10100100 9
1!
#820
0!
#825
b10100110 9
b10011 7
b10011000000 3
b10010000000 4
b10001000000 5
b1001111 :
1!
#830
0!
#835
b1010000 :
b10010000000 5
b10011000000 4
b10100 7
b10100000000 3
b10101000 9
1!
#840
0!
#845
b10101010 9
b10101 7
b10101000000 3
b10100000000 4
b10011000000 5
b1010001 :
1!
#850
0!
#855
b1010010 :
b10100000000 5
b10101000000 4
b10110 7
b10110000000 3
b10101100 9
1!
#860
0!
#865
b10101110 9
b10111 7
b10111000000 3
b10110000000 4
b10101000000 5
b1010011 :
1!
#870
0!
#875
b1010100 :
b10110000000 5
b10111000000 4
b11000 7
b11000000000 3
b10110000 9
1!
#880
0!
#885
b10110010 9
b11001 7
b11001000000 3
b11000000000 4
b10111000000 5
b1010101 :
1!
#890
0!
#895
b1010110 :
b11000000000 5
b11001000000 4
b11010 7
b11010000000 3
b10110100 9
1!
#900
0!
#905
b10110110 9
b11011 7
b11011000000 3
b11010000000 4
b11001000000 5
b1010111 :
1!
#910
0!
#915
b1011000 :
b11010000000 5
b11011000000 4
b11100 7
b11100000000 3
b10111000 9
1!
#920
0!
#925
b10111010 9
b11101 7
b11101000000 3
b11100000000 4
b11011000000 5
b1011001 :
1!
#930
0!
#935
b1011010 :
b11100000000 5
b11101000000 4
b11110 7
b11110000000 3
b10111100 9
1!
#940
0!
#945
b10111110 9
b11111 7
b11111000000 3
b11110000000 4
b11101000000 5
b1011011 :
1!
#950
0!
#955
b1011100 :
b11110000000 5
b11111000000 4
b100000 7
b100000000000 3
b11000000 9
1!
#960
0!
#965
b11000010 9
b100 8
b1 7
b100001000000 3
b100000000000 4
b11111000000 5
b1011101 :
1!
#970
0!
#975
b1011110 :
b100000000000 5
b100001000000 4
b10 7
b11000000 3
b1001 .
b1001 ;
b11000100 9
1!
#980
0!
#985
b11000110 9
b11 7
b100000000 3
b0 .
b0 ;
b11000000 4
b100001000000 5
b1011111 :
1!
#990
0!
#995
b1100000 :
b11000000 5
b100000000 4
b100 7
b101000000 3
b11001000 9
1!
#1000
0!
#1005
b11001010 9
b101 7
b110000000 3
b101000000 4
b100000000 5
b1100001 :
1!
#1010
0!
#1015
b1100010 :
b101000000 5
b110000000 4
b110 7
b111000000 3
b11001100 9
1!
#1020
0!
#1025
b11001110 9
b111 7
b1000000000 3
b111000000 4
b110000000 5
b1100011 :
1!
#1030
0!
#1035
b1100100 :
b111000000 5
b1000000000 4
b1000 7
b1001000000 3
b11010000 9
1!
#1040
0!
#1045
b11010010 9
b1001 7
b1010000000 3
b1001000000 4
b1000000000 5
b1100101 :
1!
#1050
0!
#1055
b1100110 :
b1001000000 5
b1010000000 4
b1010 7
b1011000000 3
b11010100 9
1!
#1060
0!
#1065
b11010110 9
b1011 7
b1100000000 3
b1011000000 4
b1010000000 5
b1100111 :
1!
#1070
0!
#1075
b1101000 :
b1011000000 5
b1100000000 4
b1100 7
b1101000000 3
b11011000 9
1!
#1080
0!
#1085
b11011010 9
b1101 7
b1110000000 3
b1101000000 4
b1100000000 5
b1101001 :
1!
#1090
0!
#1095
b1101010 :
b1101000000 5
b1110000000 4
b1110 7
b1111000000 3
b11011100 9
1!
#1100
0!
#1105
b11011110 9
b1111 7
b10000000000 3
b1111000000 4
b1110000000 5
b1101011 :
1!
#1110
0!
#1115
b1101100 :
b1111000000 5
b10000000000 4
b10000 7
b10001000000 3
b11100000 9
1!
#1120
0!
#1125
b11100010 9
b10001 7
b10010000000 3
b10001000000 4
b10000000000 5
b1101101 :
1!
#1130
0!
#1135
b1101110 :
b10001000000 5
b10010000000 4
b10010 7
b10011000000 3
b11100100 9
1!
#1140
0!
#1145
b11100110 9
b10011 7
b10100000000 3
b10011000000 4
b10010000000 5
b1101111 :
1!
#1150
0!
#1155
b1110000 :
b10011000000 5
b10100000000 4
b10100 7
b10101000000 3
b11101000 9
1!
#1160
0!
#1165
b11101010 9
b10101 7
b10110000000 3
b10101000000 4
b10100000000 5
b1110001 :
1!
#1170
0!
#1175
b1110010 :
b10101000000 5
b10110000000 4
b10110 7
b10111000000 3
b11101100 9
1!
#1180
0!
#1185
b11101110 9
b10111 7
b11000000000 3
b10111000000 4
b10110000000 5
b1110011 :
1!
#1190
0!
#1195
b1110100 :
b10111000000 5
b11000000000 4
b11000 7
b11001000000 3
b11110000 9
1!
#1200
0!
#1205
b11110010 9
b11001 7
b11010000000 3
b11001000000 4
b11000000000 5
b1110101 :
1!
#1210
0!
#1215
b1110110 :
b11001000000 5
b11010000000 4
b11010 7
b11011000000 3
b11110100 9
1!
#1220
0!
#1225
b11110110 9
b11011 7
b11100000000 3
b11011000000 4
b11010000000 5
b1110111 :
1!
#1230
0!
